utask/__init__.py
utask-0.0.0.dist-info/METADATA
utask-0.0.0.dist-info/WHEEL
utask-0.0.0.dist-info/licenses/LICENSE
utask-0.0.0.dist-info/RECORD
